pyblynkrestapi/BlynkClient.py
pyblynkrestapi/PyBlynkRestApi.py
pyblynkrestapi/__init__.py
pyblynkrestapi/common.py
pyblynkrestapi-0.0.2.dist-info/WHEEL
pyblynkrestapi-0.0.2.dist-info/METADATA
pyblynkrestapi-0.0.2.dist-info/RECORD
