Metadata-Version: 1.2
Name: pyblynkrestapi
Version: 0.0.2
Summary: PyBlynkRestApi  Python wrapper around the Blynk Rest API.  See documenation at:  https://github.com/youngsoul/PyBlynkRestApi
Home-page: https://github.com/youngsoul/PyBlynkRestApi
License: Unlicense
Author: Patrick Ryan
Author-email: pat_ryan_99@yahoo.com
